{"id":"tWiRMQhkmTMAi1M7mAq9","reward":{"type":"time_token","count":1},"description":"You're a good swimmer, but when you climb back on the dock, you notice both your new sunglasses and wallet are gone. Ugh.","createdAt":1611606754,"title":"Uh-oh ... your friend pushed you in","reference":"694","stats_change":{"security":-10,"happiness":-10,"wealth":-10,"money":-1800},"type":"info","updatedAt":{"_seconds":1576531766,"_nanoseconds":764013000},"next":["ncZUOOZ4Au53eLmqcxl5"],"emotion":"Very Sad","required":{"money":1800},"attachments":[]}
